{
	"name": "ABS_JSON_anyBlob",
	"properties": {
		"linkedServiceName": {
			"referenceName": "AnyBlobLinkedService",
			"type": "LinkedServiceReference",
			"parameters": {
				"ConnectionSecret": {
					"value": "@dataset().LinkedServiceConnectionSecret",
					"type": "Expression"
				}
			}
		},
		"parameters": {
			"Container": {
				"type": "string"
			},
			"Directory": {
				"type": "string",
				"defaultValue": "."
			},
			"File": {
				"type": "string",
				"defaultValue": "."
			},
			"LinkedServiceConnectionSecret": {
				"type": "string"
			}
		},
		"folder": {
			"name": "Chapter 5"
		},
		"annotations": [],
		"type": "Json",
		"typeProperties": {
			"location": {
				"type": "AzureBlobStorageLocation",
				"fileName": {
					"value": "@dataset().File",
					"type": "Expression"
				},
				"folderPath": {
					"value": "@dataset().Directory",
					"type": "Expression"
				},
				"container": {
					"value": "@dataset().Container",
					"type": "Expression"
				}
			}
		},
		"schema": {}
	}
}